pdf2chem.py
pdf2chem-0.1.6.dist-info/LICENSE
pdf2chem-0.1.6.dist-info/WHEEL
pdf2chem-0.1.6.dist-info/METADATA
pdf2chem-0.1.6.dist-info/RECORD
