Metadata-Version: 2.1
Name: pdf2chem
Version: 0.1.6
Summary: A curator for chemistry-related pdf files
Home-page: https://github.com/johngoeltz/pdf2chem
License: MIT
Keywords: chemistry,curator,pdf,SMILES
Author: johngoeltz
Author-email: 80011540+johngoeltz@users.noreply.github.com
Requires-Python: >=3.7.1,<4.0.0
Classifier: License :: OSI Approved :: MIT License
Classifier: Programming Language :: Python :: 3
Classifier: Programming Language :: Python :: 3.8
Classifier: Programming Language :: Python :: 3.9
Requires-Dist: CIRpy (>=1.0.2,<2.0.0)
Requires-Dist: ChemDataExtractor (>=1.3.0,<2.0.0)
Requires-Dist: DateTime (>=4.3,<5.0)
Requires-Dist: pandas (==1.1.5)
Requires-Dist: textract (>=1.6.3,<2.0.0)
Project-URL: Repository, https://github.com/johngoeltz/pdf2chem
